adafruit_circuitpython_tinylora-2.2.23.dist-info/licenses/LICENSE
adafruit_tinylora/__init__.py
adafruit_tinylora/adafruit_tinylora.py
adafruit_tinylora/adafruit_tinylora_encryption.py
adafruit_tinylora/ttn_as.py
adafruit_tinylora/ttn_au.py
adafruit_tinylora/ttn_cn.py
adafruit_tinylora/ttn_eu.py
adafruit_tinylora/ttn_usa.py
adafruit_circuitpython_tinylora-2.2.23.dist-info/METADATA
adafruit_circuitpython_tinylora-2.2.23.dist-info/WHEEL
adafruit_circuitpython_tinylora-2.2.23.dist-info/top_level.txt
adafruit_circuitpython_tinylora-2.2.23.dist-info/RECORD
