Metadata-Version: 2.4
Name: adafruit-circuitpython-tinylora
Version: 2.2.23
Summary: CircuitPython library for LoRaWAN and The Things Network.
Author-email: Adafruit Industries <circuitpython@adafruit.com>
License: MIT
Project-URL: Homepage, https://github.com/adafruit/Adafruit_CircuitPython_TinyLoRa
Keywords: adafruit,lorawan,thethingsnetwork,hardware,micropython,circuitpython
Classifier: Intended Audience :: Developers
Classifier: Topic :: Software Development :: Libraries
Classifier: Topic :: Software Development :: Embedded Systems
Classifier: Topic :: System :: Hardware
Classifier: License :: OSI Approved :: MIT License
Classifier: Programming Language :: Python :: 3
License-File: LICENSE
Requires-Dist: Adafruit-Blinka
Requires-Dist: adafruit-circuitpython-busdevice
Requires-Dist: typing_extensions
Provides-Extra: optional
Dynamic: license-file
